README.rst
setup.py
tornado_crontab/__init__.py
tornado_crontab/_crontab.py
tornado_crontab.egg-info/PKG-INFO
tornado_crontab.egg-info/SOURCES.txt
tornado_crontab.egg-info/dependency_links.txt
tornado_crontab.egg-info/requires.txt
tornado_crontab.egg-info/top_level.txt